protobuf_test_generator/__init__.py
protobuf_test_generator/__main__.py
protobuf_test_generator/cli.py
protobuf_test_generator/constraints/__init__.py
protobuf_test_generator/constraints/base.py
protobuf_test_generator/constraints/bufvalidate.py
protobuf_test_generator/constraints/nanopb.py
protobuf_test_generator/constraints/protovalidate.py
protobuf_test_generator/core/__init__.py
protobuf_test_generator/core/encoder.py
protobuf_test_generator/core/generator.py
protobuf_test_generator/core/parser.py
protobuf_test_generator/core/validator.py
protobuf_test_generator/formatters/__init__.py
protobuf_test_generator/formatters/base.py
protobuf_test_generator/formatters/binary.py
protobuf_test_generator/formatters/c_array.py
protobuf_test_generator/formatters/hex.py
protobuf_test_generator/formatters/json.py
protobuf_test_generator/generators/__init__.py
protobuf_test_generator/generators/enum.py
protobuf_test_generator/generators/map.py
protobuf_test_generator/generators/message.py
protobuf_test_generator/generators/numeric.py
protobuf_test_generator/generators/repeated.py
protobuf_test_generator/generators/string.py
protobuf_test_generator/utils/__init__.py
protobuf_test_generator/utils/proto_utils.py
protobuf_test_generator/utils/random_utils.py
protobuf_data_generator-1.1.0.dist-info/METADATA
protobuf_data_generator-1.1.0.dist-info/WHEEL
protobuf_data_generator-1.1.0.dist-info/entry_points.txt
protobuf_data_generator-1.1.0.dist-info/licenses/LICENSE
protobuf_data_generator-1.1.0.dist-info/RECORD
