Metadata-Version: 2.4
Name: protobuf-data-generator
Version: 1.1.0
Summary: A Python package for generating valid and invalid protobuf test data.
License: MIT
License-File: LICENSE
Keywords: protobuf,test data,data generator,nanopb,validation
Author: Ofek Almog
Author-email: ofekalm100@gmail.com
Requires-Python: >=3.8,<3.14
Classifier: License :: OSI Approved :: MIT License
Classifier: Operating System :: OS Independent
Classifier: Programming Language :: Python :: 3
Classifier: Programming Language :: Python :: 3.8
Classifier: Programming Language :: Python :: 3.9
Classifier: Programming Language :: Python :: 3.10
Classifier: Programming Language :: Python :: 3.11
Classifier: Programming Language :: Python :: 3.12
Classifier: Programming Language :: Python :: 3.13
Requires-Dist: grpcio-tools (>=1.75.1,<2.0.0)
Requires-Dist: protobuf (>=6.31.1,<7.0.0)
Project-URL: Documentation, https://github.com/OfekiAlm/protobuf-data-generator#readme
Project-URL: Homepage, https://github.com/OfekiAlm/protobuf-data-generator
Project-URL: Issue Tracker, https://github.com/OfekiAlm/protobuf-data-generator/issues
Project-URL: Repository, https://github.com/OfekiAlm/protobuf-data-generator
Project-URL: Source, https://github.com/OfekiAlm/protobuf-data-generator
